<?xml version="1.0" encoding="UTF-8"?>
<vivadoHLSLog:LogRoot xmlns:vivadoHLSLog="www.xilinx.com/vivadoHLSLog">
  <errorLogs>
    <logs>
      <synLog/>
      <simLog/>
      <mgLog/>
      <packageLog/>
      <csimLog/>
    </logs>
  </errorLogs>
  <warningLogs>
    <logs>
      <synLog>
        <logs message="WARNING: [RTGEN 206-101] Port 'out_breath' with mode 'ap_none' may require an associated data valid signal to correctly communicate with other blocks or a test bench; automatic C/RTL co-simulation may not be able to verify such a port." projectName="accelerator_v2" solutionName="solution1" date="2026-04-12T15:59:12.721-0500" type="Warning"/>
        <logs message="WARNING: [RTGEN 206-101] Port 'in_breath' with mode 'ap_none' may require an associated data valid signal to correctly communicate with other blocks or a test bench; automatic C/RTL co-simulation may not be able to verify such a port." projectName="accelerator_v2" solutionName="solution1" date="2026-04-12T15:59:12.708-0500" type="Warning"/>
        <logs message="WARNING: [RTGEN 206-101] Design contains AXI ports. Reset is fixed to synchronous and active low." projectName="accelerator_v2" solutionName="solution1" date="2026-04-12T15:59:12.598-0500" type="Warning"/>
        <logs message="WARNING: [BIND 205-102] The specified resource core for memory 'row_buf_V_3' will be ignored if a simpler one can be used." projectName="accelerator_v2" solutionName="solution1" date="2026-04-12T15:59:02.834-0500" type="Warning"/>
        <logs message="WARNING: [BIND 205-102] The specified resource core for memory 'row_buf_V' will be ignored if a simpler one can be used." projectName="accelerator_v2" solutionName="solution1" date="2026-04-12T15:59:02.829-0500" type="Warning"/>
        <logs message="WARNING: [BIND 205-102] The specified resource core for memory 'row_buf_V_2' will be ignored if a simpler one can be used." projectName="accelerator_v2" solutionName="solution1" date="2026-04-12T15:59:02.824-0500" type="Warning"/>
        <logs message="WARNING: [BIND 205-102] The specified resource core for memory 'row_buf_V_1' will be ignored if a simpler one can be used." projectName="accelerator_v2" solutionName="solution1" date="2026-04-12T15:59:02.817-0500" type="Warning"/>
        <logs message="WARNING: [SYN 201-103] Legalizing function name 'GaussianBlur&lt;5, 1, 0, 484, 644, 1, 3220, 3220>' to 'GaussianBlur_5_1_0_484_644_1_3220_3220_s'." projectName="accelerator_v2" solutionName="solution1" date="2026-04-12T15:59:01.769-0500" type="Warning"/>
        <logs message="WARNING: [SYN 201-103] Legalizing function name 'xFGaussianFilter5x5&lt;0, 484, 644, 1, 0, 1, 3220, 3220, 1, 644, false>' to 'xFGaussianFilter5x5_0_484_644_1_0_1_3220_3220_1_644_false_s'." projectName="accelerator_v2" solutionName="solution1" date="2026-04-12T15:59:01.737-0500" type="Warning"/>
        <logs message="WARNING: [SYN 201-103] Legalizing function name 'xfapplygaussian5x5&lt;1, 0, false>' to 'xfapplygaussian5x5_1_0_false_s'." projectName="accelerator_v2" solutionName="solution1" date="2026-04-12T15:59:01.732-0500" type="Warning"/>
        <logs message="WARNING: [SYN 201-103] Legalizing function name 'bgr2gray&lt;9, 0, 484, 644, 1, 3220, 3220>' to 'bgr2gray_9_0_484_644_1_3220_3220_s'." projectName="accelerator_v2" solutionName="solution1" date="2026-04-12T15:59:01.726-0500" type="Warning"/>
        <logs message="WARNING: [SYN 201-103] Legalizing function name 'bgr2gray&lt;9, 0, 484, 644, 1, 3220, 3220>_Pipeline_columnloop' to 'bgr2gray_9_0_484_644_1_3220_3220_Pipeline_columnloop'." projectName="accelerator_v2" solutionName="solution1" date="2026-04-12T15:59:01.719-0500" type="Warning"/>
        <logs message="WARNING: [HLS 200-1450] Process unpack has both a successor and writes an output to its caller (see the GUI dataflow viewer). This may lead to lower throughput. Consider copying this output via a successor process.&#xA;Resolution: For help on HLS 200-1450 see www.xilinx.com/cgi-bin/docs/rdoc?v=2022.2;t=hls+guidance;d=200-1450.html" projectName="accelerator_v2" solutionName="solution1" date="2026-04-12T15:59:01.599-0500" type="Warning"/>
        <logs message="WARNING: [XFORM 203-631] Renaming function 'xfapplygaussian5x5&lt;1, 0, false>' to 'xfapplygaussian5x5_1_0_false_s' (/misc/scratch/gwl459/augmented-reality-glasses/fpga_software/resources/Vitis_Libraries/vision/L1/include/imgproc/xf_gaussian_filter.hpp:176)" projectName="accelerator_v2" solutionName="solution1" date="2026-04-12T15:59:01.580-0500" type="Warning"/>
        <logs message="WARNING: [ANALYSIS 214-52] Found false inter dependency for variable 'blurred_mat.data' (accelerator_v2.cpp:193)." projectName="accelerator_v2" solutionName="solution1" date="2026-04-12T15:59:01.447-0500" type="Warning"/>
        <logs message="WARNING: [ANALYSIS 214-52] Found false inter dependency for variable 'gray_mat.data' (accelerator_v2.cpp:192)." projectName="accelerator_v2" solutionName="solution1" date="2026-04-12T15:59:01.380-0500" type="Warning"/>
        <logs message="WARNING: [ANALYSIS 214-52] Found false inter dependency for variable 'gray_mat.cols'." projectName="accelerator_v2" solutionName="solution1" date="2026-04-12T15:59:01.375-0500" type="Warning"/>
        <logs message="WARNING: [ANALYSIS 214-52] Found false inter dependency for variable 'gray_mat.rows'." projectName="accelerator_v2" solutionName="solution1" date="2026-04-12T15:59:01.370-0500" type="Warning"/>
        <logs message="WARNING: [ANALYSIS 214-52] Found false inter dependency for variable 'buf.V' (/misc/scratch/gwl459/augmented-reality-glasses/fpga_software/resources/Vitis_Libraries/vision/L1/include/imgproc/xf_gaussian_filter.hpp:751)." projectName="accelerator_v2" solutionName="solution1" date="2026-04-12T15:59:01.366-0500" type="Warning"/>
        <logs message="WARNING: [ANALYSIS 214-52] Found false inter dependency for variable 'buf.V.1' (/misc/scratch/gwl459/augmented-reality-glasses/fpga_software/resources/Vitis_Libraries/vision/L1/include/imgproc/xf_gaussian_filter.hpp:751)." projectName="accelerator_v2" solutionName="solution1" date="2026-04-12T15:59:01.361-0500" type="Warning"/>
        <logs message="WARNING: [ANALYSIS 214-52] Found false inter dependency for variable 'buf.V.2' (/misc/scratch/gwl459/augmented-reality-glasses/fpga_software/resources/Vitis_Libraries/vision/L1/include/imgproc/xf_gaussian_filter.hpp:751)." projectName="accelerator_v2" solutionName="solution1" date="2026-04-12T15:59:01.355-0500" type="Warning"/>
        <logs message="WARNING: [ANALYSIS 214-52] Found false inter dependency for variable 'buf.V.3' (/misc/scratch/gwl459/augmented-reality-glasses/fpga_software/resources/Vitis_Libraries/vision/L1/include/imgproc/xf_gaussian_filter.hpp:751)." projectName="accelerator_v2" solutionName="solution1" date="2026-04-12T15:59:01.350-0500" type="Warning"/>
        <logs message="WARNING: [ANALYSIS 214-52] Found false inter dependency for variable 'buf.V.4' (/misc/scratch/gwl459/augmented-reality-glasses/fpga_software/resources/Vitis_Libraries/vision/L1/include/imgproc/xf_gaussian_filter.hpp:751)." projectName="accelerator_v2" solutionName="solution1" date="2026-04-12T15:59:01.344-0500" type="Warning"/>
        <logs message="WARNING: [ANALYSIS 214-52] Found false inter dependency for variable 'blurred_mat.data' (accelerator_v2.cpp:193)." projectName="accelerator_v2" solutionName="solution1" date="2026-04-12T15:59:01.339-0500" type="Warning"/>
        <logs message="WARNING: [ANALYSIS 214-52] Found false inter dependency for variable 'gray_mat.data' (accelerator_v2.cpp:192)." projectName="accelerator_v2" solutionName="solution1" date="2026-04-12T15:59:01.326-0500" type="Warning"/>
        <logs message="WARNING: [ANALYSIS 214-52] Found false inter dependency for variable 'gray_mat.cols'." projectName="accelerator_v2" solutionName="solution1" date="2026-04-12T15:59:01.321-0500" type="Warning"/>
        <logs message="WARNING: [ANALYSIS 214-52] Found false inter dependency for variable 'gray_mat.rows'." projectName="accelerator_v2" solutionName="solution1" date="2026-04-12T15:59:01.317-0500" type="Warning"/>
        <logs message="WARNING: [ANALYSIS 214-52] Found false inter dependency for variable 'buf.V' (/misc/scratch/gwl459/augmented-reality-glasses/fpga_software/resources/Vitis_Libraries/vision/L1/include/imgproc/xf_gaussian_filter.hpp:751)." projectName="accelerator_v2" solutionName="solution1" date="2026-04-12T15:59:01.312-0500" type="Warning"/>
        <logs message="WARNING: [ANALYSIS 214-52] Found false inter dependency for variable 'buf.V.1' (/misc/scratch/gwl459/augmented-reality-glasses/fpga_software/resources/Vitis_Libraries/vision/L1/include/imgproc/xf_gaussian_filter.hpp:751)." projectName="accelerator_v2" solutionName="solution1" date="2026-04-12T15:59:01.307-0500" type="Warning"/>
        <logs message="WARNING: [ANALYSIS 214-52] Found false inter dependency for variable 'buf.V.2' (/misc/scratch/gwl459/augmented-reality-glasses/fpga_software/resources/Vitis_Libraries/vision/L1/include/imgproc/xf_gaussian_filter.hpp:751)." projectName="accelerator_v2" solutionName="solution1" date="2026-04-12T15:59:01.301-0500" type="Warning"/>
        <logs message="WARNING: [ANALYSIS 214-52] Found false inter dependency for variable 'buf.V.3' (/misc/scratch/gwl459/augmented-reality-glasses/fpga_software/resources/Vitis_Libraries/vision/L1/include/imgproc/xf_gaussian_filter.hpp:751)." projectName="accelerator_v2" solutionName="solution1" date="2026-04-12T15:59:01.296-0500" type="Warning"/>
        <logs message="WARNING: [ANALYSIS 214-52] Found false inter dependency for variable 'buf.V.4' (/misc/scratch/gwl459/augmented-reality-glasses/fpga_software/resources/Vitis_Libraries/vision/L1/include/imgproc/xf_gaussian_filter.hpp:751)." projectName="accelerator_v2" solutionName="solution1" date="2026-04-12T15:59:01.291-0500" type="Warning"/>
        <logs message="WARNING: [HLS 200-960] Cannot flatten loop 'VITIS_LOOP_134_8' (accelerator_v2.cpp:134:32) in function 'pad' the outer loop is not a perfect loop because there is nontrivial logic in the loop latch.&#xA;Resolution: For help on HLS 200-960 see www.xilinx.com/cgi-bin/docs/rdoc?v=2022.2;t=hls+guidance;d=200-960.html" projectName="accelerator_v2" solutionName="solution1" date="2026-04-12T15:59:01.189-0500" type="Warning"/>
        <logs message="WARNING: [HLS 200-960] Cannot flatten loop 'VITIS_LOOP_112_5' (accelerator_v2.cpp:112:32) in function 'pad' more than one sub loop.&#xA;Resolution: For help on HLS 200-960 see www.xilinx.com/cgi-bin/docs/rdoc?v=2022.2;t=hls+guidance;d=200-960.html" projectName="accelerator_v2" solutionName="solution1" date="2026-04-12T15:59:01.185-0500" type="Warning"/>
        <logs message="WARNING: [HLS 200-960] Cannot flatten loop 'VITIS_LOOP_100_3' (accelerator_v2.cpp:100:32) in function 'pad' the outer loop is not a perfect loop because there is nontrivial logic in the loop latch.&#xA;Resolution: For help on HLS 200-960 see www.xilinx.com/cgi-bin/docs/rdoc?v=2022.2;t=hls+guidance;d=200-960.html" projectName="accelerator_v2" solutionName="solution1" date="2026-04-12T15:59:01.180-0500" type="Warning"/>
        <logs message="WARNING: [HLS 200-960] Cannot flatten loop 'VITIS_LOOP_221_1' (accelerator_v2.cpp:223:9) in function 'repack' more than one sub loop.&#xA;Resolution: For help on HLS 200-960 see www.xilinx.com/cgi-bin/docs/rdoc?v=2022.2;t=hls+guidance;d=200-960.html" projectName="accelerator_v2" solutionName="solution1" date="2026-04-12T15:59:01.172-0500" type="Warning"/>
        <logs message="WARNING: [HLS 200-960] Cannot flatten loop 'VITIS_LOOP_39_1' (accelerator_v2.cpp:39:28) in function 'unpack' the outer loop is not a perfect loop because there is nontrivial logic before entering the inner loop.&#xA;Resolution: For help on HLS 200-960 see www.xilinx.com/cgi-bin/docs/rdoc?v=2022.2;t=hls+guidance;d=200-960.html" projectName="accelerator_v2" solutionName="solution1" date="2026-04-12T15:59:01.165-0500" type="Warning"/>
        <logs message="WARNING: [HLS 200-960] Cannot flatten loop 'Row_Loop' (/misc/scratch/gwl459/augmented-reality-glasses/fpga_software/resources/Vitis_Libraries/vision/L1/include/imgproc/xf_gaussian_filter.hpp:717:17) in function 'xf::cv::xFGaussianFilter5x5&lt;0, 484, 644, 1, 0, 1, 3220, 3220, 1, 644, false>' the outer loop is not a perfect loop because there is nontrivial logic in the loop latch.&#xA;Resolution: For help on HLS 200-960 see www.xilinx.com/cgi-bin/docs/rdoc?v=2022.2;t=hls+guidance;d=200-960.html" projectName="accelerator_v2" solutionName="solution1" date="2026-04-12T15:59:01.160-0500" type="Warning"/>
        <logs message="WARNING: [SYNCHK 200-23] /usr/local/packages/Xilinx_2022.2/Vitis_HLS/2022.2/common/technology/autopilot/ap_int_ref.h:628: variable-indexed range selection may cause suboptimal QoR." projectName="accelerator_v2" solutionName="solution1" date="2026-04-12T15:59:00.422-0500" type="Warning"/>
        <logs message="WARNING: [HLS 214-273] In function 'xf::cv::Mat&lt;9, 484, 644, 1, 3220>::init(int, int, bool)', Pragma conflict happens on 'INLINE' and DATAFLOW pragmas: Inline into dataflow region may break the canonical form (/misc/scratch/gwl459/augmented-reality-glasses/fpga_software/resources/Vitis_Libraries/vision/L1/include/common/xf_structs.hpp:605:0)" projectName="accelerator_v2" solutionName="solution1" date="2026-04-12T15:58:59.756-0500" type="Warning"/>
        <logs message="WARNING: [HLS 214-273] In function 'xf::cv::Mat&lt;0, 484, 644, 1, 3220>::init(int, int, bool)', Pragma conflict happens on 'INLINE' and DATAFLOW pragmas: Inline into dataflow region may break the canonical form (/misc/scratch/gwl459/augmented-reality-glasses/fpga_software/resources/Vitis_Libraries/vision/L1/include/common/xf_structs.hpp:605:0)" projectName="accelerator_v2" solutionName="solution1" date="2026-04-12T15:58:59.752-0500" type="Warning"/>
        <logs message="WARNING: [HLS 214-273] In function 'xf::cv::Mat&lt;0, 484, 644, 1, 3220>::Mat(int, int)', Pragma conflict happens on 'INLINE' and DATAFLOW pragmas: Inline into dataflow region may break the canonical form (/misc/scratch/gwl459/augmented-reality-glasses/fpga_software/resources/Vitis_Libraries/vision/L1/include/common/xf_structs.hpp:670:0)" projectName="accelerator_v2" solutionName="solution1" date="2026-04-12T15:58:59.747-0500" type="Warning"/>
        <logs message="WARNING: [HLS 214-273] In function 'xf::cv::Mat&lt;9, 484, 644, 1, 3220>::Mat(int, int)', Pragma conflict happens on 'INLINE' and DATAFLOW pragmas: Inline into dataflow region may break the canonical form (/misc/scratch/gwl459/augmented-reality-glasses/fpga_software/resources/Vitis_Libraries/vision/L1/include/common/xf_structs.hpp:670:0)" projectName="accelerator_v2" solutionName="solution1" date="2026-04-12T15:58:59.742-0500" type="Warning"/>
        <logs message="WARNING: [HLS 207-5292] unused parameter 'index' (/misc/scratch/gwl459/augmented-reality-glasses/fpga_software/resources/Vitis_Libraries/vision/L1/include/common/xf_structs.hpp:1530:34)" projectName="accelerator_v2" solutionName="solution1" date="2026-04-12T15:58:53.122-0500" type="Warning"/>
        <logs message="WARNING: [HLS 207-5292] unused parameter 'index' (/misc/scratch/gwl459/augmented-reality-glasses/fpga_software/resources/Vitis_Libraries/vision/L1/include/common/xf_structs.hpp:1224:102)" projectName="accelerator_v2" solutionName="solution1" date="2026-04-12T15:58:53.017-0500" type="Warning"/>
        <logs message="WARNING: [HLS 207-5292] unused parameter 'stride' (/misc/scratch/gwl459/augmented-reality-glasses/fpga_software/resources/Vitis_Libraries/vision/L1/include/common/xf_structs.hpp:1036:41)" projectName="accelerator_v2" solutionName="solution1" date="2026-04-12T15:58:53.013-0500" type="Warning"/>
        <logs message="WARNING: [HLS 207-5292] unused parameter 'index' (/misc/scratch/gwl459/augmented-reality-glasses/fpga_software/resources/Vitis_Libraries/vision/L1/include/common/xf_structs.hpp:552:20)" projectName="accelerator_v2" solutionName="solution1" date="2026-04-12T15:58:53.009-0500" type="Warning"/>
        <logs message="WARNING: [HLS 207-5292] unused parameter 'index' (/misc/scratch/gwl459/augmented-reality-glasses/fpga_software/resources/Vitis_Libraries/vision/L1/include/common/xf_structs.hpp:541:14)" projectName="accelerator_v2" solutionName="solution1" date="2026-04-12T15:58:53.005-0500" type="Warning"/>
        <logs message="WARNING: [HLS 207-5292] unused parameter '_data' (/misc/scratch/gwl459/augmented-reality-glasses/fpga_software/resources/Vitis_Libraries/vision/L1/include/common/xf_structs.hpp:528:30)" projectName="accelerator_v2" solutionName="solution1" date="2026-04-12T15:58:53.001-0500" type="Warning"/>
        <logs message="WARNING: [HLS 207-5292] unused parameter 'src' (/misc/scratch/gwl459/augmented-reality-glasses/fpga_software/resources/Vitis_Libraries/vision/L1/include/common/xf_structs.hpp:517:30)" projectName="accelerator_v2" solutionName="solution1" date="2026-04-12T15:58:52.997-0500" type="Warning"/>
        <logs message="WARNING: [HLS 207-5529] 'factor' in '#pragma HLS array_reshape' is ignored (/misc/scratch/gwl459/augmented-reality-glasses/fpga_software/resources/Vitis_Libraries/vision/L1/include/common/xf_video_mem.hpp:759:47)" projectName="accelerator_v2" solutionName="solution1" date="2026-04-12T15:58:52.992-0500" type="Warning"/>
      </synLog>
      <simLog>
        <logs message="WARNING: [Simtcl 6-197] One or more HDL objects could not be logged because of object type or size limitations.  To see details please rerun the command with -verbose (-v).&#xA;## set designtopgroup [add_wave_group &quot;Design Top Signals&quot;]&#xA;## set coutputgroup [add_wave_group &quot;C Outputs&quot; -into $designtopgroup]&#xA;## set return_group [add_wave_group return(axi_slave) -into $coutputgroup]&#xA;## add_wave /apatb_accelerator_v2_top/AESL_inst_accelerator_v2/out_stream_TREADY -into $return_group -color #ffff00 -radix hex&#xA;## add_wave /apatb_accelerator_v2_top/AESL_inst_accelerator_v2/out_stream_TVALID -into $return_group -color #ffff00 -radix hex&#xA;## add_wave /apatb_accelerator_v2_top/AESL_inst_accelerator_v2/out_breath -into $return_group -radix hex&#xA;## add_wave /apatb_accelerator_v2_top/AESL_inst_accelerator_v2/in_breath -into $return_group -radix hex&#xA;## add_wave /apatb_accelerator_v2_top/AESL_inst_accelerator_v2/out_stream_TDEST -into $return_group -radix hex&#xA;## add_wave /apatb_accelerator_v2_top/AESL_inst_accelerator_v2/out_stream_TID -into $return_group -radix hex&#xA;## add_wave /apatb_accelerator_v2_top/AESL_inst_accelerator_v2/out_stream_TLAST -into $return_group -color #ffff00 -radix hex&#xA;## add_wave /apatb_accelerator_v2_top/AESL_inst_accelerator_v2/out_stream_TUSER -into $return_group -radix hex&#xA;## add_wave /apatb_accelerator_v2_top/AESL_inst_accelerator_v2/out_stream_TSTRB -into $return_group -radix hex&#xA;## add_wave /apatb_accelerator_v2_top/AESL_inst_accelerator_v2/out_stream_TKEEP -into $return_group -radix hex&#xA;## add_wave /apatb_accelerator_v2_top/AESL_inst_accelerator_v2/out_stream_TDATA -into $return_group -radix hex&#xA;## add_wave /apatb_accelerator_v2_top/AESL_inst_accelerator_v2/interrupt -into $return_group -color #ffff00 -radix hex&#xA;## add_wave /apatb_accelerator_v2_top/AESL_inst_accelerator_v2/s_axi_CTRL_BRESP -into $return_group -radix hex&#xA;## add_wave /apatb_accelerator_v2_top/AESL_inst_accelerator_v2/s_axi_CTRL_BREADY -into $return_group -color #ffff00 -radix hex&#xA;## add_wave /apatb_accelerator_v2_top/AESL_inst_accelerator_v2/s_axi_CTRL_BVALID -into $return_group -color #ffff00 -radix hex&#xA;## add_wave /apatb_accelerator_v2_top/AESL_inst_accelerator_v2/s_axi_CTRL_RRESP -into $return_group -radix hex&#xA;## add_wave /apatb_accelerator_v2_top/AESL_inst_accelerator_v2/s_axi_CTRL_RDATA -into $return_group -radix hex&#xA;## add_wave /apatb_accelerator_v2_top/AESL_inst_accelerator_v2/s_axi_CTRL_RREADY -into $return_group -color #ffff00 -radix hex&#xA;## add_wave /apatb_accelerator_v2_top/AESL_inst_accelerator_v2/s_axi_CTRL_RVALID -into $return_group -color #ffff00 -radix hex&#xA;## add_wave /apatb_accelerator_v2_top/AESL_inst_accelerator_v2/s_axi_CTRL_ARREADY -into $return_group -color #ffff00 -radix hex&#xA;## add_wave /apatb_accelerator_v2_top/AESL_inst_accelerator_v2/s_axi_CTRL_ARVALID -into $return_group -color #ffff00 -radix hex&#xA;## add_wave /apatb_accelerator_v2_top/AESL_inst_accelerator_v2/s_axi_CTRL_ARADDR -into $return_group -radix hex&#xA;## add_wave /apatb_accelerator_v2_top/AESL_inst_accelerator_v2/s_axi_CTRL_WSTRB -into $return_group -radix hex&#xA;## add_wave /apatb_accelerator_v2_top/AESL_inst_accelerator_v2/s_axi_CTRL_WDATA -into $return_group -radix hex&#xA;## add_wave /apatb_accelerator_v2_top/AESL_inst_accelerator_v2/s_axi_CTRL_WREADY -into $return_group -color #ffff00 -radix hex&#xA;## add_wave /apatb_accelerator_v2_top/AESL_inst_accelerator_v2/s_axi_CTRL_WVALID -into $return_group -color #ffff00 -radix hex&#xA;## add_wave /apatb_accelerator_v2_top/AESL_inst_accelerator_v2/s_axi_CTRL_AWREADY -into $return_group -color #ffff00 -radix hex&#xA;## add_wave /apatb_accelerator_v2_top/AESL_inst_accelerator_v2/s_axi_CTRL_AWVALID -into $return_group -color #ffff00 -radix hex&#xA;## add_wave /apatb_accelerator_v2_top/AESL_inst_accelerator_v2/s_axi_CTRL_AWADDR -into $return_group -radix hex&#xA;## set cinputgroup [add_wave_group &quot;C Inputs&quot; -into $designtopgroup]&#xA;## set return_group [add_wave_group return(axis) -into $cinputgroup]&#xA;## add_wave /apatb_accelerator_v2_top/AESL_inst_accelerator_v2/in_stream_TREADY -into $return_group -color #ffff00 -radix hex&#xA;## add_wave /apatb_accelerator_v2_top/AESL_inst_accelerator_v2/in_stream_TVALID -into $return_group -color #ffff00 -radix hex&#xA;## add_wave /apatb_accelerator_v2_top/AESL_inst_accelerator_v2/in_stream_TDEST -into $return_group -radix hex&#xA;## add_wave /apatb_accelerator_v2_top/AESL_inst_accelerator_v2/in_stream_TID -into $return_group -radix hex&#xA;## add_wave /apatb_accelerator_v2_top/AESL_inst_accelerator_v2/in_stream_TLAST -into $return_group -color #ffff00 -radix hex&#xA;## add_wave /apatb_accelerator_v2_top/AESL_inst_accelerator_v2/in_stream_TUSER -into $return_group -radix hex&#xA;## add_wave /apatb_accelerator_v2_top/AESL_inst_accelerator_v2/in_stream_TSTRB -into $return_group -radix hex&#xA;## add_wave /apatb_accelerator_v2_top/AESL_inst_accelerator_v2/in_stream_TKEEP -into $return_group -radix hex&#xA;## add_wave /apatb_accelerator_v2_top/AESL_inst_accelerator_v2/in_stream_TDATA -into $return_group -radix hex&#xA;## set blocksiggroup [add_wave_group &quot;Block-level IO Handshake(internal)&quot; -into $designtopgroup]&#xA;## add_wave /apatb_accelerator_v2_top/AESL_inst_accelerator_v2/ap_done -into $blocksiggroup&#xA;## add_wave /apatb_accelerator_v2_top/AESL_inst_accelerator_v2/ap_idle -into $blocksiggroup&#xA;## add_wave /apatb_accelerator_v2_top/AESL_inst_accelerator_v2/ap_ready -into $blocksiggroup&#xA;## add_wave /apatb_accelerator_v2_top/AESL_inst_accelerator_v2/ap_start -into $blocksiggroup&#xA;## set resetgroup [add_wave_group &quot;Reset&quot; -into $designtopgroup]&#xA;## add_wave /apatb_accelerator_v2_top/AESL_inst_accelerator_v2/ap_rst_n -into $resetgroup&#xA;## set clockgroup [add_wave_group &quot;Clock&quot; -into $designtopgroup]&#xA;## add_wave /apatb_accelerator_v2_top/AESL_inst_accelerator_v2/ap_clk -into $clockgroup&#xA;## set testbenchgroup [add_wave_group &quot;Test Bench Signals&quot;]&#xA;## set tbinternalsiggroup [add_wave_group &quot;Internal Signals&quot; -into $testbenchgroup]&#xA;## set tb_simstatus_group [add_wave_group &quot;Simulation Status&quot; -into $tbinternalsiggroup]&#xA;## set tb_portdepth_group [add_wave_group &quot;Port Depth&quot; -into $tbinternalsiggroup]&#xA;## add_wave /apatb_accelerator_v2_top/AUTOTB_TRANSACTION_NUM -into $tb_simstatus_group -radix hex&#xA;## add_wave /apatb_accelerator_v2_top/ready_cnt -into $tb_simstatus_group -radix hex&#xA;## add_wave /apatb_accelerator_v2_top/done_cnt -into $tb_simstatus_group -radix hex&#xA;## add_wave /apatb_accelerator_v2_top/LENGTH_in_breath -into $tb_portdepth_group -radix hex&#xA;## add_wave /apatb_accelerator_v2_top/LENGTH_in_stream_V_data_V -into $tb_portdepth_group -radix hex&#xA;## add_wave /apatb_accelerator_v2_top/LENGTH_in_stream_V_dest_V -into $tb_portdepth_group -radix hex&#xA;## add_wave /apatb_accelerator_v2_top/LENGTH_in_stream_V_id_V -into $tb_portdepth_group -radix hex&#xA;## add_wave /apatb_accelerator_v2_top/LENGTH_in_stream_V_keep_V -into $tb_portdepth_group -radix hex&#xA;## add_wave /apatb_accelerator_v2_top/LENGTH_in_stream_V_last_V -into $tb_portdepth_group -radix hex&#xA;## add_wave /apatb_accelerator_v2_top/LENGTH_in_stream_V_strb_V -into $tb_portdepth_group -radix hex&#xA;## add_wave /apatb_accelerator_v2_top/LENGTH_in_stream_V_user_V -into $tb_portdepth_group -radix hex&#xA;## add_wave /apatb_accelerator_v2_top/LENGTH_out_breath -into $tb_portdepth_group -radix hex&#xA;## add_wave /apatb_accelerator_v2_top/LENGTH_out_stream_V_data_V -into $tb_portdepth_group -radix hex&#xA;## add_wave /apatb_accelerator_v2_top/LENGTH_out_stream_V_dest_V -into $tb_portdepth_group -radix hex&#xA;## add_wave /apatb_accelerator_v2_top/LENGTH_out_stream_V_id_V -into $tb_portdepth_group -radix hex&#xA;## add_wave /apatb_accelerator_v2_top/LENGTH_out_stream_V_keep_V -into $tb_portdepth_group -radix hex&#xA;## add_wave /apatb_accelerator_v2_top/LENGTH_out_stream_V_last_V -into $tb_portdepth_group -radix hex&#xA;## add_wave /apatb_accelerator_v2_top/LENGTH_out_stream_V_strb_V -into $tb_portdepth_group -radix hex&#xA;## add_wave /apatb_accelerator_v2_top/LENGTH_out_stream_V_user_V -into $tb_portdepth_group -radix hex&#xA;## set tbcoutputgroup [add_wave_group &quot;C Outputs&quot; -into $testbenchgroup]&#xA;## set tb_return_group [add_wave_group return(axi_slave) -into $tbcoutputgroup]&#xA;## add_wave /apatb_accelerator_v2_top/out_stream_TREADY -into $tb_return_group -color #ffff00 -radix hex&#xA;## add_wave /apatb_accelerator_v2_top/out_stream_TVALID -into $tb_return_group -color #ffff00 -radix hex&#xA;## add_wave /apatb_accelerator_v2_top/out_breath -into $tb_return_group -radix hex&#xA;## add_wave /apatb_accelerator_v2_top/in_breath -into $tb_return_group -radix hex&#xA;## add_wave /apatb_accelerator_v2_top/out_stream_TDEST -into $tb_return_group -radix hex&#xA;## add_wave /apatb_accelerator_v2_top/out_stream_TID -into $tb_return_group -radix hex&#xA;## add_wave /apatb_accelerator_v2_top/out_stream_TLAST -into $tb_return_group -color #ffff00 -radix hex&#xA;## add_wave /apatb_accelerator_v2_top/out_stream_TUSER -into $tb_return_group -radix hex&#xA;## add_wave /apatb_accelerator_v2_top/out_stream_TSTRB -into $tb_return_group -radix hex&#xA;## add_wave /apatb_accelerator_v2_top/out_stream_TKEEP -into $tb_return_group -radix hex&#xA;## add_wave /apatb_accelerator_v2_top/out_stream_TDATA -into $tb_return_group -radix hex&#xA;## add_wave /apatb_accelerator_v2_top/CTRL_INTERRUPT -into $tb_return_group -color #ffff00 -radix hex&#xA;## add_wave /apatb_accelerator_v2_top/CTRL_BRESP -into $tb_return_group -radix hex&#xA;## add_wave /apatb_accelerator_v2_top/CTRL_BREADY -into $tb_return_group -color #ffff00 -radix hex&#xA;## add_wave /apatb_accelerator_v2_top/CTRL_BVALID -into $tb_return_group -color #ffff00 -radix hex&#xA;## add_wave /apatb_accelerator_v2_top/CTRL_RRESP -into $tb_return_group -radix hex&#xA;## add_wave /apatb_accelerator_v2_top/CTRL_RDATA -into $tb_return_group -radix hex&#xA;## add_wave /apatb_accelerator_v2_top/CTRL_RREADY -into $tb_return_group -color #ffff00 -radix hex&#xA;## add_wave /apatb_accelerator_v2_top/CTRL_RVALID -into $tb_return_group -color #ffff00 -radix hex&#xA;## add_wave /apatb_accelerator_v2_top/CTRL_ARREADY -into $tb_return_group -color #ffff00 -radix hex&#xA;## add_wave /apatb_accelerator_v2_top/CTRL_ARVALID -into $tb_return_group -color #ffff00 -radix hex&#xA;## add_wave /apatb_accelerator_v2_top/CTRL_ARADDR -into $tb_return_group -radix hex&#xA;## add_wave /apatb_accelerator_v2_top/CTRL_WSTRB -into $tb_return_group -radix hex&#xA;## add_wave /apatb_accelerator_v2_top/CTRL_WDATA -into $tb_return_group -radix hex&#xA;## add_wave /apatb_accelerator_v2_top/CTRL_WREADY -into $tb_return_group -color #ffff00 -radix hex&#xA;## add_wave /apatb_accelerator_v2_top/CTRL_WVALID -into $tb_return_group -color #ffff00 -radix hex&#xA;## add_wave /apatb_accelerator_v2_top/CTRL_AWREADY -into $tb_return_group -color #ffff00 -radix hex&#xA;## add_wave /apatb_accelerator_v2_top/CTRL_AWVALID -into $tb_return_group -color #ffff00 -radix hex&#xA;## add_wave /apatb_accelerator_v2_top/CTRL_AWADDR -into $tb_return_group -radix hex&#xA;## set tbcinputgroup [add_wave_group &quot;C Inputs&quot; -into $testbenchgroup]&#xA;## set tb_return_group [add_wave_group return(axis) -into $tbcinputgroup]&#xA;## add_wave /apatb_accelerator_v2_top/in_stream_TREADY -into $tb_return_group -color #ffff00 -radix hex&#xA;## add_wave /apatb_accelerator_v2_top/in_stream_TVALID -into $tb_return_group -color #ffff00 -radix hex&#xA;## add_wave /apatb_accelerator_v2_top/in_stream_TDEST -into $tb_return_group -radix hex&#xA;## add_wave /apatb_accelerator_v2_top/in_stream_TID -into $tb_return_group -radix hex&#xA;## add_wave /apatb_accelerator_v2_top/in_stream_TLAST -into $tb_return_group -color #ffff00 -radix hex&#xA;## add_wave /apatb_accelerator_v2_top/in_stream_TUSER -into $tb_return_group -radix hex&#xA;## add_wave /apatb_accelerator_v2_top/in_stream_TSTRB -into $tb_return_group -radix hex&#xA;## add_wave /apatb_accelerator_v2_top/in_stream_TKEEP -into $tb_return_group -radix hex&#xA;## add_wave /apatb_accelerator_v2_top/in_stream_TDATA -into $tb_return_group -radix hex&#xA;## save_wave_config accelerator_v2.wcfg&#xA;## run all&#xA;////////////////////////////////////////////////////////////////////////////////////&#xA;// Inter-Transaction Progress: Completed Transaction / Total Transaction&#xA;// Intra-Transaction Progress: Measured Latency / Latency Estimation * 100%&#xA;//&#xA;// RTL Simulation : &quot;Inter-Transaction Progress&quot; [&quot;Intra-Transaction Progress&quot;] @ &quot;Simulation Time&quot;&#xA;////////////////////////////////////////////////////////////////////////////////////&#xA;// RTL Simulation : 0 / 1 [0.00%] @ &quot;125000&quot;&#xA;// RTL Simulation : 1 / 1 [100.00%] @ &quot;9253685000&quot;&#xA;////////////////////////////////////////////////////////////////////////////////////&#xA;$finish called at time : 9253745 ns : File &quot;/misc/scratch/gwl459/augmented-reality-glasses/fpga_software/PL/accelerator_v2/solution1/sim/verilog/accelerator_v2.autotb.v&quot; Line 552&#xA;run: Time (s): cpu = 00:13:10 ; elapsed = 00:13:30 . Memory (MB): peak = 5587.480 ; gain = 0.000 ; free physical = 228064 ; free virtual = 360747&#xA;## quit" projectName="accelerator_v2" solutionName="solution1" date="2026-04-12T16:14:00.808-0500" type="Warning"/>
        <logs message="WARNING: [VRFC 10-3645] port 'axis_block_info' remains unconnected for this instance [/misc/scratch/gwl459/augmented-reality-glasses/fpga_software/PL/accelerator_v2/solution1/sim/verilog/AESL_deadlock_kernel_monitor_top.v:40]&#xA;Completed static elaboration&#xA;Starting simulation data flow analysis&#xA;Completed simulation data flow analysis&#xA;Time Resolution for simulation is 1ps&#xA;Compiling package xil_defaultlib.$unit_dataflow_monitor_sv&#xA;Compiling module xil_defaultlib.accelerator_v2_CTRL_s_axi&#xA;Compiling module xil_defaultlib.accelerator_v2_flow_control_loop...&#xA;Compiling module xil_defaultlib.accelerator_v2_unpack_Pipeline_V...&#xA;Compiling module xil_defaultlib.accelerator_v2_regslice_both(Dat...&#xA;Compiling module xil_defaultlib.accelerator_v2_unpack&#xA;Compiling module xil_defaultlib.accelerator_v2_pad_row_buf_V_RAM...&#xA;Compiling module xil_defaultlib.accelerator_v2_pad_Pipeline_VITI...&#xA;Compiling module xil_defaultlib.accelerator_v2_mux_32_24_1_1(ID=...&#xA;Compiling module xil_defaultlib.accelerator_v2_pad_Pipeline_VITI...&#xA;Compiling module xil_defaultlib.accelerator_v2_mux_42_24_1_1(ID=...&#xA;Compiling module xil_defaultlib.accelerator_v2_pad_Pipeline_VITI...&#xA;Compiling module xil_defaultlib.accelerator_v2_mux_21_24_1_1(ID=...&#xA;Compiling module xil_defaultlib.accelerator_v2_pad_Pipeline_VITI...&#xA;Compiling module xil_defaultlib.accelerator_v2_pad&#xA;Compiling module xil_defaultlib.accelerator_v2_flow_control_loop...&#xA;Compiling module xil_defaultlib.accelerator_v2_stream_to_mat&#xA;Compiling module xil_defaultlib.accelerator_v2_mul_mul_8ns_14ns_...&#xA;Compiling module xil_defaultlib.accelerator_v2_mac_muladd_8ns_12...&#xA;Compiling module xil_defaultlib.accelerator_v2_mac_muladd_8ns_15...&#xA;Compiling module xil_defaultlib.accelerator_v2_bgr2gray_9_0_484_...&#xA;Compiling module xil_defaultlib.accelerator_v2_xFGaussianFilter5...&#xA;Compiling module xil_defaultlib.accelerator_v2_ama_addmuladd_8ns...&#xA;Compiling module xil_defaultlib.accelerator_v2_mac_muladd_8ns_7n...&#xA;Compiling module xil_defaultlib.accelerator_v2_mac_muladd_24ns_7...&#xA;Compiling module xil_defaultlib.accelerator_v2_xfapplygaussian5x...&#xA;Compiling module xil_defaultlib.accelerator_v2_xFGaussianFilter5...&#xA;Compiling module xil_defaultlib.accelerator_v2_mux_53_8_1_1(ID=1...&#xA;Compiling module xil_defaultlib.accelerator_v2_xFGaussianFilter5...&#xA;Compiling module xil_defaultlib.accelerator_v2_GaussianBlur_5_1_...&#xA;Compiling module xil_defaultlib.accelerator_v2_mat_to_stream&#xA;Compiling module xil_defaultlib.accelerator_v2_fifo_w24_d3220_A_...&#xA;Compiling module xil_defaultlib.accelerator_v2_fifo_w24_d3220_A&#xA;Compiling module xil_defaultlib.accelerator_v2_fifo_w8_d3220_A_r...&#xA;Compiling module xil_defaultlib.accelerator_v2_fifo_w8_d3220_A&#xA;Compiling module xil_defaultlib.accelerator_v2_start_for_bgr2gra...&#xA;Compiling module xil_defaultlib.accelerator_v2_start_for_Gaussia...&#xA;Compiling module xil_defaultlib.accelerator_v2_start_for_mat_to_...&#xA;Compiling module xil_defaultlib.accelerator_v2_process_pixels&#xA;Compiling module xil_defaultlib.accelerator_v2_repack_row_pixels...&#xA;Compiling module xil_defaultlib.accelerator_v2_repack_Pipeline_V...&#xA;Compiling module xil_defaultlib.accelerator_v2_repack&#xA;Compiling module xil_defaultlib.accelerator_v2_fifo_w24_d2560_A_...&#xA;Compiling module xil_defaultlib.accelerator_v2_fifo_w24_d2560_A&#xA;Compiling module xil_defaultlib.accelerator_v2_fifo_w24_d2576_A_...&#xA;Compiling module xil_defaultlib.accelerator_v2_fifo_w24_d2576_A&#xA;Compiling module xil_defaultlib.accelerator_v2_fifo_w8_d3864_A_r...&#xA;Compiling module xil_defaultlib.accelerator_v2_fifo_w8_d3864_A&#xA;Compiling module xil_defaultlib.accelerator_v2_start_for_pad_U0_...&#xA;Compiling module xil_defaultlib.accelerator_v2_start_for_pad_U0&#xA;Compiling module xil_defaultlib.accelerator_v2_start_for_process...&#xA;Compiling module xil_defaultlib.accelerator_v2_start_for_repack_...&#xA;Compiling module xil_defaultlib.accelerator_v2&#xA;Compiling module xil_defaultlib.fifo(DEPTH=57696,WIDTH=128)&#xA;Compiling module xil_defaultlib.fifo(DEPTH=57696,WIDTH=16)&#xA;Compiling module xil_defaultlib.fifo(DEPTH=57696,WIDTH=1)&#xA;Compiling module xil_defaultlib.AESL_axi_s_in_stream&#xA;Compiling module xil_defaultlib.fifo(DEPTH=19680,WIDTH=128)&#xA;Compiling module xil_defaultlib.fifo(DEPTH=19680,WIDTH=16)&#xA;Compiling module xil_defaultlib.fifo(DEPTH=19680,WIDTH=1)&#xA;Compiling module xil_defaultlib.AESL_axi_s_out_stream&#xA;Compiling module xil_defaultlib.AESL_axi_slave_CTRL&#xA;Compiling module xil_defaultlib.AESL_deadlock_detect_unit(PROC_N...&#xA;Compiling module xil_defaultlib.AESL_deadlock_report_unit(PROC_N...&#xA;Compiling module xil_defaultlib.AESL_deadlock_detector_1&#xA;Compiling module xil_defaultlib.AESL_deadlock_idx1_monitor&#xA;Compiling module xil_defaultlib.AESL_deadlock_idx3_monitor&#xA;Compiling module xil_defaultlib.AESL_deadlock_idx0_monitor&#xA;Compiling module xil_defaultlib.AESL_deadlock_kernel_monitor_top...&#xA;Compiling module xil_defaultlib.df_fifo_intf&#xA;Compiling module xil_defaultlib.df_process_intf&#xA;Compiling module xil_defaultlib.nodf_module_intf&#xA;Compiling module xil_defaultlib.seq_loop_intf(FSM_WIDTH=4)&#xA;Compiling module xil_defaultlib.seq_loop_intf(FSM_WIDTH=29)&#xA;Compiling module xil_defaultlib.seq_loop_intf(FSM_WIDTH=3)&#xA;Compiling module xil_defaultlib.seq_loop_intf(FSM_WIDTH=17)&#xA;Compiling module xil_defaultlib.seq_loop_intf(FSM_WIDTH=8)&#xA;Compiling module xil_defaultlib.upc_loop_intf(FSM_WIDTH=1)&#xA;Compiling module xil_defaultlib.dataflow_monitor_1&#xA;Compiling module xil_defaultlib.apatb_accelerator_v2_top&#xA;Compiling module work.glbl&#xA;Built simulation snapshot accelerator_v2&#xA;&#xA;&#xA;****** xsim v2022.2 (64-bit)&#xA;  **** SW Build 3671981 on Fri Oct 14 04:59:54 MDT 2022&#xA;  **** IP Build 3669848 on Fri Oct 14 08:30:02 MDT 2022&#xA;    ** Copyright 1986-2022 Xilinx, Inc. All Rights Reserved.&#xA;&#xA;&#xA;source xsim.dir/accelerator_v2/xsim_script.tcl&#xA;# xsim {accelerator_v2} -view {{accelerator_v2_dataflow_ana.wcfg}} -tclbatch {accelerator_v2.tcl} -protoinst {accelerator_v2.protoinst}" projectName="accelerator_v2" solutionName="solution1" date="2026-04-12T16:00:30.078-0500" type="Warning"/>
      </simLog>
      <mgLog/>
      <packageLog/>
      <csimLog/>
    </logs>
  </warningLogs>
</vivadoHLSLog:LogRoot>
