<profile>

<ReportVersion>
<Version>2022.2</Version>
</ReportVersion>

<UserAssignments>
<unit>ns</unit>
<ProductFamily>virtexuplus</ProductFamily>
<Part>xcvu11p-flga2577-1-e</Part>
<TopModelName>pad_Pipeline_VITIS_LOOP_116_9</TopModelName>
<TargetClockPeriod>10.00</TargetClockPeriod>
<ClockUncertainty>2.70</ClockUncertainty>
<FlowTarget>vivado</FlowTarget>
</UserAssignments>

<PerformanceEstimates>
<PipelineType>no</PipelineType>
<SummaryOfTimingAnalysis>
<unit>ns</unit>
<EstimatedClockPeriod>3.483</EstimatedClockPeriod>
</SummaryOfTimingAnalysis>
<SummaryOfOverallLatency>
<unit>clock cycles</unit>
<Best-caseLatency>642</Best-caseLatency>
<Average-caseLatency>642</Average-caseLatency>
<Worst-caseLatency>642</Worst-caseLatency>
<Best-caseRealTimeLatency>6.420 us</Best-caseRealTimeLatency>
<Average-caseRealTimeLatency>6.420 us</Average-caseRealTimeLatency>
<Worst-caseRealTimeLatency>6.420 us</Worst-caseRealTimeLatency>
<Interval-min>642</Interval-min>
<Interval-max>642</Interval-max>
</SummaryOfOverallLatency>
<SummaryOfLoopLatency>
<VITIS_LOOP_116_9>
<Slack>7.30</Slack>
<TripCount>640</TripCount>
<Latency>640</Latency>
<AbsoluteTimeLatency>6400</AbsoluteTimeLatency>
<PipelineII>1</PipelineII>
<PipelineDepth>2</PipelineDepth>
<InstanceList>
</InstanceList>
</VITIS_LOOP_116_9>
</SummaryOfLoopLatency>
</PerformanceEstimates>

<AreaEstimates>
<Resources>
<FF>13</FF>
<LUT>86</LUT>
<BRAM_18K>0</BRAM_18K>
<DSP>0</DSP>
<URAM>0</URAM>
</Resources>
<AvailableResources>
<BRAM_18K>4032</BRAM_18K>
<DSP>9216</DSP>
<FF>2592000</FF>
<LUT>1296000</LUT>
<URAM>960</URAM>
</AvailableResources>
</AreaEstimates>

<InterfaceSummary>
<RtlPorts>
<name>ap_clk</name>
<Object>pad_Pipeline_VITIS_LOOP_116_9</Object>
<Type>return value</Type>
<Scope></Scope>
<IOProtocol>ap_ctrl_hs</IOProtocol>
<IOConfig></IOConfig>
<Dir>in</Dir>
<Bits>1</Bits>
<Attribute>control</Attribute>
</RtlPorts>
<RtlPorts>
<name>ap_rst</name>
<Object>pad_Pipeline_VITIS_LOOP_116_9</Object>
<Type>return value</Type>
<Scope></Scope>
<IOProtocol>ap_ctrl_hs</IOProtocol>
<IOConfig></IOConfig>
<Dir>in</Dir>
<Bits>1</Bits>
<Attribute>control</Attribute>
</RtlPorts>
<RtlPorts>
<name>ap_start</name>
<Object>pad_Pipeline_VITIS_LOOP_116_9</Object>
<Type>return value</Type>
<Scope></Scope>
<IOProtocol>ap_ctrl_hs</IOProtocol>
<IOConfig></IOConfig>
<Dir>in</Dir>
<Bits>1</Bits>
<Attribute>control</Attribute>
</RtlPorts>
<RtlPorts>
<name>ap_done</name>
<Object>pad_Pipeline_VITIS_LOOP_116_9</Object>
<Type>return value</Type>
<Scope></Scope>
<IOProtocol>ap_ctrl_hs</IOProtocol>
<IOConfig></IOConfig>
<Dir>out</Dir>
<Bits>1</Bits>
<Attribute>control</Attribute>
</RtlPorts>
<RtlPorts>
<name>ap_idle</name>
<Object>pad_Pipeline_VITIS_LOOP_116_9</Object>
<Type>return value</Type>
<Scope></Scope>
<IOProtocol>ap_ctrl_hs</IOProtocol>
<IOConfig></IOConfig>
<Dir>out</Dir>
<Bits>1</Bits>
<Attribute>control</Attribute>
</RtlPorts>
<RtlPorts>
<name>ap_ready</name>
<Object>pad_Pipeline_VITIS_LOOP_116_9</Object>
<Type>return value</Type>
<Scope></Scope>
<IOProtocol>ap_ctrl_hs</IOProtocol>
<IOConfig></IOConfig>
<Dir>out</Dir>
<Bits>1</Bits>
<Attribute>control</Attribute>
</RtlPorts>
<RtlPorts>
<name>padded_stream2_din</name>
<Object>padded_stream2</Object>
<Type>pointer</Type>
<Scope></Scope>
<IOProtocol>ap_fifo</IOProtocol>
<IOConfig></IOConfig>
<Dir>out</Dir>
<Bits>24</Bits>
<Attribute>control</Attribute>
</RtlPorts>
<RtlPorts>
<name>padded_stream2_num_data_valid</name>
<Object>padded_stream2</Object>
<Type>pointer</Type>
<Scope></Scope>
<IOProtocol>ap_fifo</IOProtocol>
<IOConfig></IOConfig>
<Dir>in</Dir>
<Bits>20</Bits>
<Attribute>control</Attribute>
</RtlPorts>
<RtlPorts>
<name>padded_stream2_fifo_cap</name>
<Object>padded_stream2</Object>
<Type>pointer</Type>
<Scope></Scope>
<IOProtocol>ap_fifo</IOProtocol>
<IOConfig></IOConfig>
<Dir>in</Dir>
<Bits>20</Bits>
<Attribute>unknown</Attribute>
</RtlPorts>
<RtlPorts>
<name>padded_stream2_full_n</name>
<Object>padded_stream2</Object>
<Type>pointer</Type>
<Scope></Scope>
<IOProtocol>ap_fifo</IOProtocol>
<IOConfig></IOConfig>
<Dir>in</Dir>
<Bits>1</Bits>
<Attribute>control</Attribute>
</RtlPorts>
<RtlPorts>
<name>padded_stream2_write</name>
<Object>padded_stream2</Object>
<Type>pointer</Type>
<Scope></Scope>
<IOProtocol>ap_fifo</IOProtocol>
<IOConfig></IOConfig>
<Dir>out</Dir>
<Bits>1</Bits>
<Attribute>control</Attribute>
</RtlPorts>
<RtlPorts>
<name>row_buf_V_2_address0</name>
<Object>row_buf_V_2</Object>
<Type>array</Type>
<Scope></Scope>
<IOProtocol>ap_memory</IOProtocol>
<IOConfig></IOConfig>
<Dir>out</Dir>
<Bits>10</Bits>
<Attribute>address</Attribute>
</RtlPorts>
<RtlPorts>
<name>row_buf_V_2_ce0</name>
<Object>row_buf_V_2</Object>
<Type>array</Type>
<Scope></Scope>
<IOProtocol>ap_memory</IOProtocol>
<IOConfig></IOConfig>
<Dir>out</Dir>
<Bits>1</Bits>
<Attribute>control</Attribute>
</RtlPorts>
<RtlPorts>
<name>row_buf_V_2_q0</name>
<Object>row_buf_V_2</Object>
<Type>array</Type>
<Scope></Scope>
<IOProtocol>ap_memory</IOProtocol>
<IOConfig></IOConfig>
<Dir>in</Dir>
<Bits>24</Bits>
<Attribute>data</Attribute>
</RtlPorts>
<RtlPorts>
<name>row_buf_V_3_address0</name>
<Object>row_buf_V_3</Object>
<Type>array</Type>
<Scope></Scope>
<IOProtocol>ap_memory</IOProtocol>
<IOConfig></IOConfig>
<Dir>out</Dir>
<Bits>10</Bits>
<Attribute>address</Attribute>
</RtlPorts>
<RtlPorts>
<name>row_buf_V_3_ce0</name>
<Object>row_buf_V_3</Object>
<Type>array</Type>
<Scope></Scope>
<IOProtocol>ap_memory</IOProtocol>
<IOConfig></IOConfig>
<Dir>out</Dir>
<Bits>1</Bits>
<Attribute>control</Attribute>
</RtlPorts>
<RtlPorts>
<name>row_buf_V_3_q0</name>
<Object>row_buf_V_3</Object>
<Type>array</Type>
<Scope></Scope>
<IOProtocol>ap_memory</IOProtocol>
<IOConfig></IOConfig>
<Dir>in</Dir>
<Bits>24</Bits>
<Attribute>data</Attribute>
</RtlPorts>
<RtlPorts>
<name>r_5_cast</name>
<Object>r_5_cast</Object>
<Type>scalar</Type>
<Scope></Scope>
<IOProtocol>ap_none</IOProtocol>
<IOConfig></IOConfig>
<Dir>in</Dir>
<Bits>1</Bits>
<Attribute>data</Attribute>
</RtlPorts>
</InterfaceSummary>

</profile>
